{
  "version": "7",
  "dialect": "sqlite",
  "entries": [
    {
      "idx": 0,
      "version": "6",
      "when": 1776887567933,
      "tag": "0000_dazzling_steve_rogers",
      "breakpoints": true
    },
    {
      "idx": 1,
      "version": "6",
      "when": 1776924291780,
      "tag": "0001_medical_chat",
      "breakpoints": true
    },
    {
      "idx": 2,
      "version": "6",
      "when": 1776925207918,
      "tag": "0002_amazing_bloodstrike",
      "breakpoints": true
    },
    {
      "idx": 3,
      "version": "6",
      "when": 1776925709487,
      "tag": "0003_spooky_hemingway",
      "breakpoints": true
    },
    {
      "idx": 4,
      "version": "6",
      "when": 1776979051655,
      "tag": "0004_amused_nekra",
      "breakpoints": true
    },
    {
      "idx": 5,
      "version": "6",
      "when": 1776981823513,
      "tag": "0005_hot_bromley",
      "breakpoints": true
    },
    {
      "idx": 6,
      "version": "6",
      "when": 1776983682192,
      "tag": "0006_eager_eternity",
      "breakpoints": true
    }
  ]
}